federatedsecure/server/__init__.py
federatedsecure/server/bus.py
federatedsecure/server/discovery.py
federatedsecure/server/exceptions.py
federatedsecure/server/registry.py
federatedsecure/server/utils.py
federatedsecure/services/sync/__init__.py
federatedsecure/services/sync/barrier.py
federatedsecure/services/sync/broadcast.py
federatedsecure/services/util/__init__.py
federatedsecure/services/util/kvstorage.py
federatedsecure_server-0.6.3.dist-info/METADATA
federatedsecure_server-0.6.3.dist-info/WHEEL
federatedsecure_server-0.6.3.dist-info/top_level.txt
federatedsecure_server-0.6.3.dist-info/RECORD
